config_generator/__init__.py
config_generator/configurator.py
config_generator-1.3.dist-info/METADATA
config_generator-1.3.dist-info/WHEEL
config_generator-1.3.dist-info/top_level.txt
config_generator-1.3.dist-info/RECORD
