Metadata-Version: 2.1
Name: config-generator
Version: 1.3
Requires-Dist: pydantic>=2.8
